power_bdd/__init__.py
power_bdd/bdd.py
power_bdd/node.py
power_bdd/tests/__init__.py
power_bdd/tests/test_bdd.py
power_bdd-1.0.0.dist-info/METADATA
power_bdd-1.0.0.dist-info/WHEEL
power_bdd-1.0.0.dist-info/licenses/LICENSE
power_bdd-1.0.0.dist-info/RECORD
