Metadata-Version: 2.1
Name: power_bdd
Version: 1.0.0
Summary: Calculates power indices (Banzhaf/Penrose, Shapley/Shubik) via binary decision diagrams
Project-URL: Homepage, https://github.com/oceanwhiskey/power_bdd
Project-URL: Bug Tracker, https://github.com/oceanwhiskey/power_bdd/issues
Author-email: Ingo Wilms <ingo.wilms@gmail.com>
License: Copyright (c) 2022 Ingo Wilms
License-File: LICENSE
Classifier: License :: OSI Approved :: MIT License
Classifier: Operating System :: OS Independent
Classifier: Programming Language :: Python :: 3
Requires-Python: >=3.7
Requires-Dist: sortedcontainers>=2.0
